putki/__init__.py
putki/__main__.py
putki/api.py
putki/cli.py
putki/discover.py
putki/things.py
putki/traverse.py
putki-2023.11.29.dist-info/LICENSE
putki-2023.11.29.dist-info/METADATA
putki-2023.11.29.dist-info/WHEEL
putki-2023.11.29.dist-info/entry_points.txt
putki-2023.11.29.dist-info/top_level.txt
putki-2023.11.29.dist-info/RECORD
